{"workflow":{"name":"ggggg","issue":"0","type":"support","currencyid":"0","default":"0","changeType":"0","term":"0","issuename":false,"outcoming":"0","keywords":"","showOrderMenu":"0","calendarInfo":"","gridInfo":"","tableInfo":"","emploerInfo":"","timelineInfo":"","pipelineInfo":"","chatInfo":"","repaymentour":"0","repaymentin":"0"},"statuses":{"510":{"name":"1","default":"1","payed":"0","saled":"0","sort":"1","content":"","x":"0","y":"0","width":"0","height":"0","colour":"","term":"0","termperiod":"","onlyauto":"0","onlyissue":"0","closed":"0","shipped":"0","autorepeat":"0","nextdate":""},"511":{"name":"2","default":"0","payed":"0","saled":"0","sort":"2","content":"","x":"150","y":"0","width":"0","height":"0","colour":"","term":"0","termperiod":"","onlyauto":"0","onlyissue":"0","closed":"0","shipped":"0","autorepeat":"0","nextdate":""}},"interfaceData":{"1":{"id":"1","name":"translate_box_name_small","contentid":"box-admin-block-name","priority":"0","categoryname":"translate_name_and_issue_info","customSettings":"0","ismobile":"0","index":"0","integration":"","blockSettings":""},"2":{"id":"2","name":"translate_shapka_biznesprotsessa","contentid":"box-admin-block-header","priority":"0","categoryname":"translate_name_and_issue_info","customSettings":"1","ismobile":"0","index":"0","integration":"","blockSettings":""},"3":{"id":"3","name":"translate_last_client_event","contentid":"box-admin-block-last-client-event","priority":"0","categoryname":"translate_contacts_and_dop_pola","customSettings":"1","ismobile":"0","index":"0","integration":"","blockSettings":""},"4":{"id":"4","name":"translate_payments","contentid":"box-admin-block-order-payment-table","priority":"0","categoryname":"translate_cash","customSettings":"1","ismobile":"0","index":"0","integration":"","blockSettings":""},"5":{"id":"5","name":"translate_poslednie_rezultati_zapolneniya_form_klienta","contentid":"box-admin-block-last-client-forms-result","priority":"0","categoryname":"translate_contacts_and_dop_pola","customSettings":"0","ismobile":"0","index":"0","integration":"","blockSettings":""},"6":{"id":"6","name":"translate_identifikatsiya_klienta","contentid":"box-admin-block-order-customer-identification","priority":"0","categoryname":"translate_name_and_issue_info","customSettings":"1","ismobile":"0","index":"0","integration":"","blockSettings":""},"7":{"id":"7","name":"translate_ob_edinit_zakazi","contentid":"box-admin-block-combine-orders","priority":"0","categoryname":"translate_name_and_issue_info","customSettings":"0","ismobile":"0","index":"0","integration":"","blockSettings":""},"8":{"id":"8","name":"translate_description","contentid":"box-admin-block-description","priority":"0","categoryname":"translate_name_and_issue_info","customSettings":"0","ismobile":"0","index":"0","integration":"","blockSettings":""},"9":{"id":"9","name":"translate_instruktsiya_k_etapu","contentid":"box-admin-block-stage-instruction","priority":"0","categoryname":"translate_name_and_issue_info","customSettings":"1","ismobile":"0","index":"0","integration":"","blockSettings":""},"10":{"id":"10","name":"translate_istoriya_statusov","contentid":"box-admin-block-stage-history","priority":"0","categoryname":"translate_orders_status_and_comments","customSettings":"1","ismobile":"0","index":"0","integration":"","blockSettings":""},"11":{"id":"11","name":"translate_karusel_izobrazheniy_produktov_zakaza","contentid":"box-admin-block-orderproduct-image-carousel","priority":"0","categoryname":"translate_many_products","customSettings":"0","ismobile":"0","index":"0","integration":"","blockSettings":""},"12":{"id":"12","name":"translate_spisok_aktivnih_zakazov","contentid":"box-admin-block-active-order","priority":"0","categoryname":"translate_proekt_and_other_bp","customSettings":"0","ismobile":"0","index":"0","integration":"","blockSettings":""},"13":{"id":"13","name":"translate_prognoz_perekhoda_na_etap","contentid":"box-admin-block-status-prognosis","priority":"0","categoryname":"translate_proekt_and_other_bp","customSettings":"1","ismobile":"0","index":"0","integration":"","blockSettings":""},"14":{"id":"14","name":"translate_spisok_aktivnih_zakazov_v_etom_bp","contentid":"box-admin-block-active-order-workflow","priority":"0","categoryname":"translate_proekt_and_other_bp","customSettings":"0","ismobile":"0","index":"0","integration":"","blockSettings":""},"15":{"id":"15","name":"translate_itogovaya_chast_zakaza","contentid":"box-admin-block-product-list-total-sum","priority":"11","categoryname":"translate_name_and_issue_info","customSettings":"1","ismobile":"0","index":"0","integration":"","blockSettings":""},"16":{"id":"16","name":"translate_knopka_dobavleniya_produkta_v_protsess","contentid":"box-admin-block-addorderproduct","priority":"0","categoryname":"translate_many_products","customSettings":"1","ismobile":"0","index":"0","integration":"","blockSettings":""},"17":{"id":"17","name":"translate_knopka_dobavleniya_produkta_v_protsess 1","contentid":"box-admin-block-addorderproduct","priority":"0","categoryname":"translate_many_products","customSettings":"1","ismobile":"0","index":"1","integration":"","blockSettings":""},"18":{"id":"18","name":"translate_knopka_dobavleniya_produkta_v_protsess 2","contentid":"box-admin-block-addorderproduct","priority":"0","categoryname":"translate_many_products","customSettings":"1","ismobile":"0","index":"2","integration":"","blockSettings":""},"19":{"id":"19","name":"translate_knopka_dobavleniya_produkta_v_protsess 3","contentid":"box-admin-block-addorderproduct","priority":"0","categoryname":"translate_many_products","customSettings":"1","ismobile":"0","index":"3","integration":"","blockSettings":""},"20":{"id":"20","name":"translate_knopka_dobavleniya_produkta_v_protsess 4","contentid":"box-admin-block-addorderproduct","priority":"0","categoryname":"translate_many_products","customSettings":"1","ismobile":"0","index":"4","integration":"","blockSettings":""},"21":{"id":"21","name":"translate_knopka_dobavleniya_produkta_v_protsess 5","contentid":"box-admin-block-addorderproduct","priority":"0","categoryname":"translate_many_products","customSettings":"1","ismobile":"0","index":"5","integration":"","blockSettings":""},"22":{"id":"22","name":"translate_knopka_dobavleniya_produkta_v_protsess 6","contentid":"box-admin-block-addorderproduct","priority":"0","categoryname":"translate_many_products","customSettings":"1","ismobile":"0","index":"6","integration":"","blockSettings":""},"23":{"id":"23","name":"translate_knopka_dobavleniya_produkta_v_protsess 7","contentid":"box-admin-block-addorderproduct","priority":"0","categoryname":"translate_many_products","customSettings":"1","ismobile":"0","index":"7","integration":"","blockSettings":""},"24":{"id":"24","name":"translate_knopka_dobavleniya_produkta_v_protsess 8","contentid":"box-admin-block-addorderproduct","priority":"0","categoryname":"translate_many_products","customSettings":"1","ismobile":"0","index":"8","integration":"","blockSettings":""},"25":{"id":"25","name":"translate_knopka_dobavleniya_produkta_v_protsess 9","contentid":"box-admin-block-addorderproduct","priority":"0","categoryname":"translate_many_products","customSettings":"1","ismobile":"0","index":"9","integration":"","blockSettings":""},"26":{"id":"26","name":"translate_many_products_intable","contentid":"box-admin-block-product-list-table","priority":"8","categoryname":"translate_many_products","customSettings":"1","ismobile":"0","index":"0","integration":"","blockSettings":""},"27":{"id":"27","name":"translate_many_products_intable","contentid":"box-admin-block-product-list-table","priority":"8","categoryname":"translate_many_products","customSettings":"1","ismobile":"0","index":"1","integration":"","blockSettings":""},"28":{"id":"28","name":"translate_many_products_intable","contentid":"box-admin-block-product-list-table","priority":"8","categoryname":"translate_many_products","customSettings":"1","ismobile":"0","index":"2","integration":"","blockSettings":""},"29":{"id":"29","name":"translate_many_products_intable","contentid":"box-admin-block-product-list-table","priority":"8","categoryname":"translate_many_products","customSettings":"1","ismobile":"0","index":"3","integration":"","blockSettings":""},"30":{"id":"30","name":"translate_many_products_intable","contentid":"box-admin-block-product-list-table","priority":"8","categoryname":"translate_many_products","customSettings":"1","ismobile":"0","index":"4","integration":"","blockSettings":""},"31":{"id":"31","name":"translate_many_products_intable","contentid":"box-admin-block-product-list-table","priority":"8","categoryname":"translate_many_products","customSettings":"1","ismobile":"0","index":"5","integration":"","blockSettings":""},"32":{"id":"32","name":"translate_many_products_intable","contentid":"box-admin-block-product-list-table","priority":"8","categoryname":"translate_many_products","customSettings":"1","ismobile":"0","index":"6","integration":"","blockSettings":""},"33":{"id":"33","name":"translate_many_products_intable","contentid":"box-admin-block-product-list-table","priority":"8","categoryname":"translate_many_products","customSettings":"1","ismobile":"0","index":"7","integration":"","blockSettings":""},"34":{"id":"34","name":"translate_many_products_intable","contentid":"box-admin-block-product-list-table","priority":"8","categoryname":"translate_many_products","customSettings":"1","ismobile":"0","index":"8","integration":"","blockSettings":""},"35":{"id":"35","name":"translate_many_products_intable","contentid":"box-admin-block-product-list-table","priority":"8","categoryname":"translate_many_products","customSettings":"1","ismobile":"0","index":"9","integration":"","blockSettings":""},"36":{"id":"36","name":"translate_many_products_inlist","contentid":"box-admin-block-product-list","priority":"9","categoryname":"translate_many_products","customSettings":"1","ismobile":"0","index":"0","integration":"","blockSettings":""},"40":{"id":"40","name":"translate_blok_podprotsesov","contentid":"box-admin-block-child-issue-table-view","priority":"0","categoryname":"translate_proekt_and_other_bp","customSettings":"1","ismobile":"0","index":"0","integration":"","blockSettings":""},"41":{"id":"41","name":"translate_blok_podprotsesov","contentid":"box-admin-block-child-issue-table-view","priority":"0","categoryname":"translate_proekt_and_other_bp","customSettings":"1","ismobile":"0","index":"4","integration":"","blockSettings":""},"42":{"id":"42","name":"translate_blok_podprotsesov","contentid":"box-admin-block-child-issue-table-view","priority":"0","categoryname":"translate_proekt_and_other_bp","customSettings":"1","ismobile":"0","index":"5","integration":"","blockSettings":""},"43":{"id":"43","name":"translate_struktura translate_proekta","contentid":"box-admin-block-issue-structure","priority":"0","categoryname":"translate_name_and_issue_info","customSettings":"1","ismobile":"0","index":"0","integration":"","blockSettings":""},"44":{"id":"44","name":"translate_lenta_kommentariev","contentid":"box-admin-block-comment-list","priority":"10","categoryname":"translate_orders_status_and_comments","customSettings":"1","ismobile":"0","index":"0","integration":"","blockSettings":""},"45":{"id":"45","name":"translate_poslednie_kommentarii_po_drugim_zakazam_klienta","contentid":"box-admin-block-last-client-order-comments","priority":"0","categoryname":"translate_orders_status_and_comments","customSettings":"1","ismobile":"0","index":"0","integration":"","blockSettings":""},"46":{"id":"46","name":"translate_informatsiya_o_kontakte_polnaya","contentid":"box-admin-block-client-info","priority":"0","categoryname":"translate_contacts_and_dop_pola","customSettings":"0","ismobile":"0","index":"0","integration":"","blockSettings":""},"47":{"id":"47","name":"translate_informatsiya_o_statuse","contentid":"box-admin-block-status-info","priority":"0","categoryname":"translate_orders_status_and_comments","customSettings":"0","ismobile":"0","index":"0","integration":"","blockSettings":""},"48":{"id":"48","name":"translate_ostavsheesya_vremya_do_ukazannoy_dati","contentid":"box-admin-block-time-info","priority":"0","categoryname":"translate_name_and_issue_info","customSettings":"1","ismobile":"0","index":"0","integration":"","blockSettings":""},"49":{"id":"49","name":"translate_grafik_aktivnosti_proekta","contentid":"box-admin-block-graph-activities","priority":"0","categoryname":"translate_proekt_and_other_bp","customSettings":"0","ismobile":"0","index":"0","integration":"","blockSettings":""},"50":{"id":"50","name":"translate_grafik_nagruzki_na_ispolniteley_proekta","contentid":"box-admin-block-graph-load","priority":"0","categoryname":"translate_proekt_and_other_bp","customSettings":"0","ismobile":"0","index":"0","integration":"","blockSettings":""},"51":{"id":"51","name":"translate_blok_dostupnikh_aktsiy_dlya_protsessa","contentid":"box-order-get-share-by-order","priority":"0","categoryname":"translate_name_and_issue_info","customSettings":"1","ismobile":"0","index":"0","integration":"","blockSettings":""},"52":{"id":"52","name":"translate_vizualizatsiya_biznesprotsessa","contentid":"box-admin-block-workflow-visual","priority":"0","categoryname":"translate_proekt_and_other_bp","customSettings":"0","ismobile":"0","index":"0","integration":"","blockSettings":""},"53":{"id":"53","name":"translate_produkti_sokrashchenniy","contentid":"box-admin-block-product-list-short","priority":"0","categoryname":"translate_many_products","customSettings":"0","ismobile":"0","index":"0","integration":"","blockSettings":""},"54":{"id":"54","name":"translate_vlozhennie_fayli","contentid":"box-admin-block-files","priority":"0","categoryname":"translate_name_and_issue_info","customSettings":"1","ismobile":"0","index":"0","integration":"","blockSettings":""},"55":{"id":"55","name":"translate_nastraivaemaya_panel_faylov","contentid":"box-admin-block-upload-files","priority":"0","categoryname":"translate_name_and_issue_info","customSettings":"1","ismobile":"0","index":"0","integration":"","blockSettings":""},"56":{"id":"56","name":"translate_vnesti_rezultat","contentid":"box-admin-block-make-result","priority":"0","categoryname":"translate_actions","customSettings":"0","ismobile":"0","index":"0","integration":"","blockSettings":""},"57":{"id":"57","name":"translate_write_letter","contentid":"box-admin-block-write-letter","priority":"0","categoryname":"translate_actions","customSettings":"0","ismobile":"0","index":"0","integration":"","blockSettings":""},"58":{"id":"58","name":"translate_pozvonit","contentid":"box-admin-block-call","priority":"0","categoryname":"translate_actions","customSettings":"0","ismobile":"0","index":"0","integration":"","blockSettings":""},"59":{"id":"59","name":"translate_zapolnit_kartochku_kontakta","contentid":"box-admin-block-user-card-fill","priority":"0","categoryname":"translate_contacts_and_dop_pola","customSettings":"1","ismobile":"0","index":"0","integration":"","blockSettings":""},"60":{"id":"60","name":"translate_zapolnit_kartochku_kompanii_klienta","contentid":"box-admin-block-user-company-card-fill","priority":"0","categoryname":"translate_contacts_and_dop_pola","customSettings":"1","ismobile":"0","index":"0","integration":"","blockSettings":""},"61":{"id":"61","name":"translate_order_contacts","contentid":"box-admin-block-order-contacts","priority":"0","categoryname":"translate_contacts_and_dop_pola","customSettings":"1","ismobile":"0","index":"0","integration":"","blockSettings":""},"62":{"id":"62","name":"translate_adresa_klienta_s_vozmozhnostyu_imenovat_kazhdiy_adres","contentid":"box-admin-block-order-client-custom-address","priority":"0","categoryname":"translate_contacts_and_dop_pola","customSettings":"1","ismobile":"0","index":"0","integration":"","blockSettings":""},"63":{"id":"63","name":"translate_itogovie_summi_chislovih_poley_podprotsessov","contentid":"box-admin-block-order-sum-customfields","priority":"0","categoryname":"translate_contacts_and_dop_pola","customSettings":"1","ismobile":"0","index":"0","integration":"","blockSettings":""},"64":{"id":"64","name":"translate_blok_zagruzki_produktov_zakaza","contentid":"box-admin-block-import-products","priority":"0","categoryname":"translate_many_products","customSettings":"1","ismobile":"0","index":"0","integration":"","blockSettings":""},"65":{"id":"65","name":"translate_mass_issue_submit","contentid":"box-admin-block-issues-add","priority":"0","categoryname":"translate_proekt_and_other_bp","customSettings":"1","ismobile":"0","index":"0","integration":"","blockSettings":""},"66":{"id":"66","name":"translate_pohozhie_zadachi","contentid":"box-admin-block-issues-like","priority":"0","categoryname":"translate_proekt_and_other_bp","customSettings":"0","ismobile":"0","index":"0","integration":"","blockSettings":""},"67":{"id":"67","name":"translate_moi_order_cabinet","contentid":"box-admin-block-my-order","priority":"0","categoryname":"translate_proekt_and_other_bp","customSettings":"0","ismobile":"0","index":"0","integration":"","blockSettings":""},"68":{"id":"68","name":"translate_spisok_zadach_proekta","contentid":"box-admin-block-project-order","priority":"0","categoryname":"translate_proekt_and_other_bp","customSettings":"1","ismobile":"0","index":"0","integration":"","blockSettings":""},"69":{"id":"69","name":"translate_baza_znaniy_proekta","contentid":"box-admin-block-standards","priority":"0","categoryname":"translate_poisk_i_baza_znaniy","customSettings":"0","ismobile":"0","index":"0","integration":"","blockSettings":""},"70":{"id":"70","name":"translate_poisk_po_baze_znaniy","contentid":"box-admin-block-standards-search-answer","priority":"0","categoryname":"translate_poisk_i_baza_znaniy","customSettings":"0","ismobile":"0","index":"0","integration":"","blockSettings":""},"71":{"id":"71","name":"translate_spisok_prosmotrennih_klientom_produktov","contentid":"box-productview-order-block","priority":"0","categoryname":"translate_contacts_and_dop_pola","customSettings":"0","ismobile":"0","index":"0","integration":"","blockSettings":""},"72":{"id":"72","name":"translate_kurs_valyut_zakaza","contentid":"box-admin-block-currency","priority":"0","categoryname":"translate_dilivery_payment","customSettings":"1","ismobile":"0","index":"0","integration":"","blockSettings":""},"73":{"id":"73","name":"translate_kto_prosmatrival_protsess","contentid":"box-admin-block-whoviewed","priority":"0","categoryname":"translate_useful","customSettings":"1","ismobile":"0","index":"0","integration":"","blockSettings":""},"74":{"id":"74","name":"translate_tekushchaya_tsel_proekta","contentid":"box-admin-block-target","priority":"0","categoryname":"translate_proekt_and_other_bp","customSettings":"0","ismobile":"0","index":"0","integration":"","blockSettings":""},"75":{"id":"75","name":"translate_poisk_produktov","contentid":"box-product-search-order-block","priority":"0","categoryname":"translate_poisk_i_baza_znaniy","customSettings":"1","ismobile":"0","index":"0","integration":"","blockSettings":""},"76":{"id":"76","name":"translate_barcode_search","contentid":"box-product-search-order-block-barcode","priority":"0","categoryname":"translate_poisk_i_baza_znaniy","customSettings":"1","ismobile":"0","index":"0","integration":"","blockSettings":""},"77":{"id":"77","name":"translate_proverit_nalichie_tovarov_v_zakaze_po_shtrihkodu","contentid":"box-product-check-order-block-barcode","priority":"0","categoryname":"translate_many_products","customSettings":"1","ismobile":"0","index":"0","integration":"","blockSettings":""},"78":{"id":"78","name":"translate_universalniy_blok","contentid":"box-admin-block-universal-fillds","priority":"0","categoryname":"translate_universalnie_bloki","customSettings":"1","ismobile":"0","index":"1","integration":"","blockSettings":""},"79":{"id":"79","name":"translate_universalniy_blok","contentid":"box-admin-block-universal-fillds","priority":"0","categoryname":"translate_universalnie_bloki","customSettings":"1","ismobile":"0","index":"2","integration":"","blockSettings":""},"80":{"id":"80","name":"translate_universalniy_blok","contentid":"box-admin-block-universal-fillds","priority":"0","categoryname":"translate_universalnie_bloki","customSettings":"1","ismobile":"0","index":"3","integration":"","blockSettings":""},"81":{"id":"81","name":"translate_universalniy_blok","contentid":"box-admin-block-universal-fillds","priority":"0","categoryname":"translate_universalnie_bloki","customSettings":"1","ismobile":"0","index":"4","integration":"","blockSettings":""},"82":{"id":"82","name":"translate_universalniy_blok","contentid":"box-admin-block-universal-fillds","priority":"0","categoryname":"translate_universalnie_bloki","customSettings":"1","ismobile":"0","index":"5","integration":"","blockSettings":""},"83":{"id":"83","name":"translate_universalniy_blok","contentid":"box-admin-block-universal-fillds","priority":"0","categoryname":"translate_universalnie_bloki","customSettings":"1","ismobile":"0","index":"6","integration":"","blockSettings":""},"84":{"id":"84","name":"translate_universalniy_blok","contentid":"box-admin-block-universal-fillds","priority":"0","categoryname":"translate_universalnie_bloki","customSettings":"1","ismobile":"0","index":"7","integration":"","blockSettings":""},"85":{"id":"85","name":"translate_universalniy_blok","contentid":"box-admin-block-universal-fillds","priority":"0","categoryname":"translate_universalnie_bloki","customSettings":"1","ismobile":"0","index":"8","integration":"","blockSettings":""},"86":{"id":"86","name":"translate_universalniy_blok","contentid":"box-admin-block-universal-fillds","priority":"0","categoryname":"translate_universalnie_bloki","customSettings":"1","ismobile":"0","index":"9","integration":"","blockSettings":""},"87":{"id":"87","name":"translate_universalniy_blok","contentid":"box-admin-block-universal-fillds","priority":"0","categoryname":"translate_universalnie_bloki","customSettings":"1","ismobile":"0","index":"10","integration":"","blockSettings":""},"88":{"id":"88","name":"translate_universalniy_blok","contentid":"box-admin-block-universal-fillds","priority":"0","categoryname":"translate_universalnie_bloki","customSettings":"1","ismobile":"0","index":"11","integration":"","blockSettings":""},"89":{"id":"89","name":"translate_universalniy_blok","contentid":"box-admin-block-universal-fillds","priority":"0","categoryname":"translate_universalnie_bloki","customSettings":"1","ismobile":"0","index":"12","integration":"","blockSettings":""},"90":{"id":"90","name":"translate_universalniy_blok","contentid":"box-admin-block-universal-fillds","priority":"0","categoryname":"translate_universalnie_bloki","customSettings":"1","ismobile":"0","index":"13","integration":"","blockSettings":""},"91":{"id":"91","name":"translate_universalniy_blok","contentid":"box-admin-block-universal-fillds","priority":"0","categoryname":"translate_universalnie_bloki","customSettings":"1","ismobile":"0","index":"14","integration":"","blockSettings":""},"92":{"id":"92","name":"translate_universalniy_blok","contentid":"box-admin-block-universal-fillds","priority":"0","categoryname":"translate_universalnie_bloki","customSettings":"1","ismobile":"0","index":"15","integration":"","blockSettings":""},"93":{"id":"93","name":"translate_universalniy_blok","contentid":"box-admin-block-universal-fillds","priority":"0","categoryname":"translate_universalnie_bloki","customSettings":"1","ismobile":"0","index":"16","integration":"","blockSettings":""},"94":{"id":"94","name":"translate_universalniy_blok","contentid":"box-admin-block-universal-fillds","priority":"0","categoryname":"translate_universalnie_bloki","customSettings":"1","ismobile":"0","index":"17","integration":"","blockSettings":""},"95":{"id":"95","name":"translate_universalniy_blok","contentid":"box-admin-block-universal-fillds","priority":"0","categoryname":"translate_universalnie_bloki","customSettings":"1","ismobile":"0","index":"18","integration":"","blockSettings":""},"96":{"id":"96","name":"translate_universalniy_blok","contentid":"box-admin-block-universal-fillds","priority":"0","categoryname":"translate_universalnie_bloki","customSettings":"1","ismobile":"0","index":"19","integration":"","blockSettings":""},"97":{"id":"97","name":"translate_universalniy_blok","contentid":"box-admin-block-universal-fillds","priority":"0","categoryname":"translate_universalnie_bloki","customSettings":"1","ismobile":"0","index":"20","integration":"","blockSettings":""},"98":{"id":"98","name":"translate_universalniy_blok","contentid":"box-admin-block-universal-fillds","priority":"0","categoryname":"translate_universalnie_bloki","customSettings":"1","ismobile":"0","index":"21","integration":"","blockSettings":""},"99":{"id":"99","name":"translate_universalniy_blok","contentid":"box-admin-block-universal-fillds","priority":"0","categoryname":"translate_universalnie_bloki","customSettings":"1","ismobile":"0","index":"22","integration":"","blockSettings":""},"100":{"id":"100","name":"translate_universalniy_blok","contentid":"box-admin-block-universal-fillds","priority":"0","categoryname":"translate_universalnie_bloki","customSettings":"1","ismobile":"0","index":"23","integration":"","blockSettings":""},"101":{"id":"101","name":"translate_universalniy_blok","contentid":"box-admin-block-universal-fillds","priority":"0","categoryname":"translate_universalnie_bloki","customSettings":"1","ismobile":"0","index":"24","integration":"","blockSettings":""},"102":{"id":"102","name":"translate_universalniy_blok","contentid":"box-admin-block-universal-fillds","priority":"0","categoryname":"translate_universalnie_bloki","customSettings":"1","ismobile":"0","index":"25","integration":"","blockSettings":""},"103":{"id":"103","name":"translate_universalniy_blok","contentid":"box-admin-block-universal-fillds","priority":"0","categoryname":"translate_universalnie_bloki","customSettings":"1","ismobile":"0","index":"26","integration":"","blockSettings":""},"104":{"id":"104","name":"translate_universalniy_blok","contentid":"box-admin-block-universal-fillds","priority":"0","categoryname":"translate_universalnie_bloki","customSettings":"1","ismobile":"0","index":"27","integration":"","blockSettings":""},"105":{"id":"105","name":"translate_universalniy_blok","contentid":"box-admin-block-universal-fillds","priority":"0","categoryname":"translate_universalnie_bloki","customSettings":"1","ismobile":"0","index":"28","integration":"","blockSettings":""},"106":{"id":"106","name":"translate_universalniy_blok","contentid":"box-admin-block-universal-fillds","priority":"0","categoryname":"translate_universalnie_bloki","customSettings":"1","ismobile":"0","index":"29","integration":"","blockSettings":""},"107":{"id":"107","name":"translate_universalniy_blok","contentid":"box-admin-block-universal-fillds","priority":"0","categoryname":"translate_universalnie_bloki","customSettings":"1","ismobile":"0","index":"30","integration":"","blockSettings":""},"108":{"id":"108","name":"translate_universalniy_blok","contentid":"box-admin-block-universal-fillds","priority":"0","categoryname":"translate_universalnie_bloki","customSettings":"1","ismobile":"0","index":"31","integration":"","blockSettings":""},"109":{"id":"109","name":"translate_universalniy_blok","contentid":"box-admin-block-universal-fillds","priority":"0","categoryname":"translate_universalnie_bloki","customSettings":"1","ismobile":"0","index":"32","integration":"","blockSettings":""},"110":{"id":"110","name":"translate_universalniy_blok","contentid":"box-admin-block-universal-fillds","priority":"0","categoryname":"translate_universalnie_bloki","customSettings":"1","ismobile":"0","index":"33","integration":"","blockSettings":""},"111":{"id":"111","name":"translate_universalniy_blok","contentid":"box-admin-block-universal-fillds","priority":"0","categoryname":"translate_universalnie_bloki","customSettings":"1","ismobile":"0","index":"34","integration":"","blockSettings":""},"112":{"id":"112","name":"translate_universalniy_blok","contentid":"box-admin-block-universal-fillds","priority":"0","categoryname":"translate_universalnie_bloki","customSettings":"1","ismobile":"0","index":"35","integration":"","blockSettings":""},"113":{"id":"113","name":"translate_universalniy_blok","contentid":"box-admin-block-universal-fillds","priority":"0","categoryname":"translate_universalnie_bloki","customSettings":"1","ismobile":"0","index":"36","integration":"","blockSettings":""},"114":{"id":"114","name":"translate_universalniy_blok","contentid":"box-admin-block-universal-fillds","priority":"0","categoryname":"translate_universalnie_bloki","customSettings":"1","ismobile":"0","index":"37","integration":"","blockSettings":""},"115":{"id":"115","name":"translate_universalniy_blok","contentid":"box-admin-block-universal-fillds","priority":"0","categoryname":"translate_universalnie_bloki","customSettings":"1","ismobile":"0","index":"38","integration":"","blockSettings":""},"116":{"id":"116","name":"translate_universalniy_blok","contentid":"box-admin-block-universal-fillds","priority":"0","categoryname":"translate_universalnie_bloki","customSettings":"1","ismobile":"0","index":"39","integration":"","blockSettings":""},"117":{"id":"117","name":"translate_universalniy_blok","contentid":"box-admin-block-universal-fillds","priority":"0","categoryname":"translate_universalnie_bloki","customSettings":"1","ismobile":"0","index":"40","integration":"","blockSettings":""},"118":{"id":"118","name":"translate_universalniy_blok","contentid":"box-admin-block-universal-fillds","priority":"0","categoryname":"translate_universalnie_bloki","customSettings":"1","ismobile":"0","index":"41","integration":"","blockSettings":""},"119":{"id":"119","name":"translate_universalniy_blok","contentid":"box-admin-block-universal-fillds","priority":"0","categoryname":"translate_universalnie_bloki","customSettings":"1","ismobile":"0","index":"42","integration":"","blockSettings":""},"120":{"id":"120","name":"translate_universalniy_blok","contentid":"box-admin-block-universal-fillds","priority":"0","categoryname":"translate_universalnie_bloki","customSettings":"1","ismobile":"0","index":"43","integration":"","blockSettings":""},"121":{"id":"121","name":"translate_universalniy_blok","contentid":"box-admin-block-universal-fillds","priority":"0","categoryname":"translate_universalnie_bloki","customSettings":"1","ismobile":"0","index":"44","integration":"","blockSettings":""},"122":{"id":"122","name":"translate_universalniy_blok","contentid":"box-admin-block-universal-fillds","priority":"0","categoryname":"translate_universalnie_bloki","customSettings":"1","ismobile":"0","index":"45","integration":"","blockSettings":""},"123":{"id":"123","name":"translate_universalniy_blok","contentid":"box-admin-block-universal-fillds","priority":"0","categoryname":"translate_universalnie_bloki","customSettings":"1","ismobile":"0","index":"46","integration":"","blockSettings":""},"124":{"id":"124","name":"translate_universalniy_blok","contentid":"box-admin-block-universal-fillds","priority":"0","categoryname":"translate_universalnie_bloki","customSettings":"1","ismobile":"0","index":"47","integration":"","blockSettings":""},"125":{"id":"125","name":"translate_universalniy_blok","contentid":"box-admin-block-universal-fillds","priority":"0","categoryname":"translate_universalnie_bloki","customSettings":"1","ismobile":"0","index":"48","integration":"","blockSettings":""},"126":{"id":"126","name":"translate_universalniy_blok","contentid":"box-admin-block-universal-fillds","priority":"0","categoryname":"translate_universalnie_bloki","customSettings":"1","ismobile":"0","index":"49","integration":"","blockSettings":""},"127":{"id":"127","name":"translate_universalniy_blok","contentid":"box-admin-block-universal-fillds","priority":"0","categoryname":"translate_universalnie_bloki","customSettings":"1","ismobile":"0","index":"50","integration":"","blockSettings":""},"128":{"id":"128","name":"translate_universalniy_blok","contentid":"box-admin-block-universal-fillds","priority":"0","categoryname":"translate_universalnie_bloki","customSettings":"1","ismobile":"0","index":"51","integration":"","blockSettings":""},"129":{"id":"129","name":"translate_universalniy_blok","contentid":"box-admin-block-universal-fillds","priority":"0","categoryname":"translate_universalnie_bloki","customSettings":"1","ismobile":"0","index":"52","integration":"","blockSettings":""},"130":{"id":"130","name":"translate_universalniy_blok","contentid":"box-admin-block-universal-fillds","priority":"0","categoryname":"translate_universalnie_bloki","customSettings":"1","ismobile":"0","index":"53","integration":"","blockSettings":""},"131":{"id":"131","name":"translate_universalniy_blok","contentid":"box-admin-block-universal-fillds","priority":"0","categoryname":"translate_universalnie_bloki","customSettings":"1","ismobile":"0","index":"54","integration":"","blockSettings":""},"132":{"id":"132","name":"translate_universalniy_blok","contentid":"box-admin-block-universal-fillds","priority":"0","categoryname":"translate_universalnie_bloki","customSettings":"1","ismobile":"0","index":"55","integration":"","blockSettings":""},"133":{"id":"133","name":"translate_universalniy_blok","contentid":"box-admin-block-universal-fillds","priority":"0","categoryname":"translate_universalnie_bloki","customSettings":"1","ismobile":"0","index":"56","integration":"","blockSettings":""},"134":{"id":"134","name":"translate_universalniy_blok","contentid":"box-admin-block-universal-fillds","priority":"0","categoryname":"translate_universalnie_bloki","customSettings":"1","ismobile":"0","index":"57","integration":"","blockSettings":""},"135":{"id":"135","name":"translate_universalniy_blok","contentid":"box-admin-block-universal-fillds","priority":"0","categoryname":"translate_universalnie_bloki","customSettings":"1","ismobile":"0","index":"58","integration":"","blockSettings":""},"136":{"id":"136","name":"translate_universalniy_blok","contentid":"box-admin-block-universal-fillds","priority":"0","categoryname":"translate_universalnie_bloki","customSettings":"1","ismobile":"0","index":"59","integration":"","blockSettings":""},"137":{"id":"137","name":"translate_universalniy_blok","contentid":"box-admin-block-universal-fillds","priority":"0","categoryname":"translate_universalnie_bloki","customSettings":"1","ismobile":"0","index":"60","integration":"","blockSettings":""},"138":{"id":"138","name":"translate_universalniy_blok","contentid":"box-admin-block-universal-fillds","priority":"0","categoryname":"translate_universalnie_bloki","customSettings":"1","ismobile":"0","index":"61","integration":"","blockSettings":""},"139":{"id":"139","name":"translate_universalniy_blok","contentid":"box-admin-block-universal-fillds","priority":"0","categoryname":"translate_universalnie_bloki","customSettings":"1","ismobile":"0","index":"62","integration":"","blockSettings":""},"140":{"id":"140","name":"translate_universalniy_blok","contentid":"box-admin-block-universal-fillds","priority":"0","categoryname":"translate_universalnie_bloki","customSettings":"1","ismobile":"0","index":"63","integration":"","blockSettings":""},"141":{"id":"141","name":"translate_universalniy_blok","contentid":"box-admin-block-universal-fillds","priority":"0","categoryname":"translate_universalnie_bloki","customSettings":"1","ismobile":"0","index":"64","integration":"","blockSettings":""},"142":{"id":"142","name":"translate_universalniy_blok","contentid":"box-admin-block-universal-fillds","priority":"0","categoryname":"translate_universalnie_bloki","customSettings":"1","ismobile":"0","index":"65","integration":"","blockSettings":""},"143":{"id":"143","name":"translate_universalniy_blok","contentid":"box-admin-block-universal-fillds","priority":"0","categoryname":"translate_universalnie_bloki","customSettings":"1","ismobile":"0","index":"66","integration":"","blockSettings":""},"144":{"id":"144","name":"translate_universalniy_blok","contentid":"box-admin-block-universal-fillds","priority":"0","categoryname":"translate_universalnie_bloki","customSettings":"1","ismobile":"0","index":"67","integration":"","blockSettings":""},"145":{"id":"145","name":"translate_universalniy_blok","contentid":"box-admin-block-universal-fillds","priority":"0","categoryname":"translate_universalnie_bloki","customSettings":"1","ismobile":"0","index":"68","integration":"","blockSettings":""},"146":{"id":"146","name":"translate_universalniy_blok","contentid":"box-admin-block-universal-fillds","priority":"0","categoryname":"translate_universalnie_bloki","customSettings":"1","ismobile":"0","index":"69","integration":"","blockSettings":""},"147":{"id":"147","name":"translate_universalniy_blok","contentid":"box-admin-block-universal-fillds","priority":"0","categoryname":"translate_universalnie_bloki","customSettings":"1","ismobile":"0","index":"70","integration":"","blockSettings":""},"148":{"id":"148","name":"translate_universalniy_blok","contentid":"box-admin-block-universal-fillds","priority":"0","categoryname":"translate_universalnie_bloki","customSettings":"1","ismobile":"0","index":"71","integration":"","blockSettings":""},"149":{"id":"149","name":"translate_universalniy_blok","contentid":"box-admin-block-universal-fillds","priority":"0","categoryname":"translate_universalnie_bloki","customSettings":"1","ismobile":"0","index":"72","integration":"","blockSettings":""},"150":{"id":"150","name":"translate_universalniy_blok","contentid":"box-admin-block-universal-fillds","priority":"0","categoryname":"translate_universalnie_bloki","customSettings":"1","ismobile":"0","index":"73","integration":"","blockSettings":""},"151":{"id":"151","name":"translate_universalniy_blok","contentid":"box-admin-block-universal-fillds","priority":"0","categoryname":"translate_universalnie_bloki","customSettings":"1","ismobile":"0","index":"74","integration":"","blockSettings":""},"152":{"id":"152","name":"translate_universalniy_blok","contentid":"box-admin-block-universal-fillds","priority":"0","categoryname":"translate_universalnie_bloki","customSettings":"1","ismobile":"0","index":"75","integration":"","blockSettings":""},"153":{"id":"153","name":"translate_universalniy_blok","contentid":"box-admin-block-universal-fillds","priority":"0","categoryname":"translate_universalnie_bloki","customSettings":"1","ismobile":"0","index":"76","integration":"","blockSettings":""},"154":{"id":"154","name":"translate_universalniy_blok","contentid":"box-admin-block-universal-fillds","priority":"0","categoryname":"translate_universalnie_bloki","customSettings":"1","ismobile":"0","index":"77","integration":"","blockSettings":""},"155":{"id":"155","name":"translate_universalniy_blok","contentid":"box-admin-block-universal-fillds","priority":"0","categoryname":"translate_universalnie_bloki","customSettings":"1","ismobile":"0","index":"78","integration":"","blockSettings":""},"156":{"id":"156","name":"translate_universalniy_blok","contentid":"box-admin-block-universal-fillds","priority":"0","categoryname":"translate_universalnie_bloki","customSettings":"1","ismobile":"0","index":"79","integration":"","blockSettings":""},"157":{"id":"157","name":"translate_universalniy_blok","contentid":"box-admin-block-universal-fillds","priority":"0","categoryname":"translate_universalnie_bloki","customSettings":"1","ismobile":"0","index":"80","integration":"","blockSettings":""},"158":{"id":"158","name":"translate_universalniy_blok","contentid":"box-admin-block-universal-fillds","priority":"0","categoryname":"translate_universalnie_bloki","customSettings":"1","ismobile":"0","index":"81","integration":"","blockSettings":""},"159":{"id":"159","name":"translate_universalniy_blok","contentid":"box-admin-block-universal-fillds","priority":"0","categoryname":"translate_universalnie_bloki","customSettings":"1","ismobile":"0","index":"82","integration":"","blockSettings":""},"160":{"id":"160","name":"translate_universalniy_blok","contentid":"box-admin-block-universal-fillds","priority":"0","categoryname":"translate_universalnie_bloki","customSettings":"1","ismobile":"0","index":"83","integration":"","blockSettings":""},"161":{"id":"161","name":"translate_universalniy_blok","contentid":"box-admin-block-universal-fillds","priority":"0","categoryname":"translate_universalnie_bloki","customSettings":"1","ismobile":"0","index":"84","integration":"","blockSettings":""},"162":{"id":"162","name":"translate_universalniy_blok","contentid":"box-admin-block-universal-fillds","priority":"0","categoryname":"translate_universalnie_bloki","customSettings":"1","ismobile":"0","index":"85","integration":"","blockSettings":""},"163":{"id":"163","name":"translate_universalniy_blok","contentid":"box-admin-block-universal-fillds","priority":"0","categoryname":"translate_universalnie_bloki","customSettings":"1","ismobile":"0","index":"86","integration":"","blockSettings":""},"164":{"id":"164","name":"translate_universalniy_blok","contentid":"box-admin-block-universal-fillds","priority":"0","categoryname":"translate_universalnie_bloki","customSettings":"1","ismobile":"0","index":"87","integration":"","blockSettings":""},"165":{"id":"165","name":"translate_universalniy_blok","contentid":"box-admin-block-universal-fillds","priority":"0","categoryname":"translate_universalnie_bloki","customSettings":"1","ismobile":"0","index":"88","integration":"","blockSettings":""},"166":{"id":"166","name":"translate_universalniy_blok","contentid":"box-admin-block-universal-fillds","priority":"0","categoryname":"translate_universalnie_bloki","customSettings":"1","ismobile":"0","index":"89","integration":"","blockSettings":""},"167":{"id":"167","name":"translate_universalniy_blok","contentid":"box-admin-block-universal-fillds","priority":"0","categoryname":"translate_universalnie_bloki","customSettings":"1","ismobile":"0","index":"90","integration":"","blockSettings":""},"168":{"id":"168","name":"translate_universalniy_blok","contentid":"box-admin-block-universal-fillds","priority":"0","categoryname":"translate_universalnie_bloki","customSettings":"1","ismobile":"0","index":"91","integration":"","blockSettings":""},"169":{"id":"169","name":"translate_universalniy_blok","contentid":"box-admin-block-universal-fillds","priority":"0","categoryname":"translate_universalnie_bloki","customSettings":"1","ismobile":"0","index":"92","integration":"","blockSettings":""},"170":{"id":"170","name":"translate_universalniy_blok","contentid":"box-admin-block-universal-fillds","priority":"0","categoryname":"translate_universalnie_bloki","customSettings":"1","ismobile":"0","index":"93","integration":"","blockSettings":""},"171":{"id":"171","name":"translate_universalniy_blok","contentid":"box-admin-block-universal-fillds","priority":"0","categoryname":"translate_universalnie_bloki","customSettings":"1","ismobile":"0","index":"94","integration":"","blockSettings":""},"172":{"id":"172","name":"translate_universalniy_blok","contentid":"box-admin-block-universal-fillds","priority":"0","categoryname":"translate_universalnie_bloki","customSettings":"1","ismobile":"0","index":"95","integration":"","blockSettings":""},"173":{"id":"173","name":"translate_universalniy_blok","contentid":"box-admin-block-universal-fillds","priority":"0","categoryname":"translate_universalnie_bloki","customSettings":"1","ismobile":"0","index":"96","integration":"","blockSettings":""},"174":{"id":"174","name":"translate_universalniy_blok","contentid":"box-admin-block-universal-fillds","priority":"0","categoryname":"translate_universalnie_bloki","customSettings":"1","ismobile":"0","index":"97","integration":"","blockSettings":""},"175":{"id":"175","name":"translate_universalniy_blok","contentid":"box-admin-block-universal-fillds","priority":"0","categoryname":"translate_universalnie_bloki","customSettings":"1","ismobile":"0","index":"98","integration":"","blockSettings":""},"176":{"id":"176","name":"translate_universalniy_blok","contentid":"box-admin-block-universal-fillds","priority":"0","categoryname":"translate_universalnie_bloki","customSettings":"1","ismobile":"0","index":"99","integration":"","blockSettings":""},"177":{"id":"177","name":"translate_universalniy_blok","contentid":"box-admin-block-universal-fillds","priority":"0","categoryname":"translate_universalnie_bloki","customSettings":"1","ismobile":"0","index":"100","integration":"","blockSettings":""},"178":{"id":"178","name":"translate_zatrachenoe_vremya","contentid":"box-timelog-order-block","priority":"0","categoryname":"translate_name_and_issue_info","customSettings":"0","ismobile":"0","index":"0","integration":"","blockSettings":""},"179":{"id":"179","name":"translate_dobavit_produkti_v_protsess_po_kodam_iz_pisma","contentid":"box-add-orderproduct-by-codes","priority":"0","categoryname":"translate_many_products","customSettings":"1","ismobile":"0","index":"0","integration":"","blockSettings":""},"180":{"id":"180","name":"translate_zakazi_klientakolichestvo","contentid":"box-user-customorder-type-count","priority":"0","categoryname":"translate_proekt_and_other_bp","customSettings":"1","ismobile":"0","index":"0","integration":"","blockSettings":""},"181":{"id":"181","name":"translate_komissiy","contentid":"box-admin-block-issues-sum-commission","priority":"0","categoryname":"translate_dilivery_payment","customSettings":"0","ismobile":"0","index":"0","integration":"","blockSettings":""},"182":{"id":"182","name":"translate_zametka","contentid":"box-admin-block-order-zametka","priority":"0","categoryname":"translate_name_and_issue_info","customSettings":"0","ismobile":"0","index":"0","integration":"","blockSettings":""},"183":{"id":"183","name":"translate_informatsiya_so_spravochnika_","contentid":"box-block-show-info-by-directory","priority":"0","categoryname":"translate_name_and_issue_info","customSettings":"1","ismobile":"0","index":"0","integration":"","blockSettings":""},"184":{"id":"184","name":"translate_informatsiya_so_spravochnika_","contentid":"box-block-show-info-by-directory","priority":"0","categoryname":"translate_name_and_issue_info","customSettings":"1","ismobile":"0","index":"1","integration":"","blockSettings":""},"185":{"id":"185","name":"translate_informatsiya_so_spravochnika_","contentid":"box-block-show-info-by-directory","priority":"0","categoryname":"translate_name_and_issue_info","customSettings":"1","ismobile":"0","index":"2","integration":"","blockSettings":""},"186":{"id":"186","name":"translate_informatsiya_so_spravochnika_","contentid":"box-block-show-info-by-directory","priority":"0","categoryname":"translate_name_and_issue_info","customSettings":"1","ismobile":"0","index":"3","integration":"","blockSettings":""},"187":{"id":"187","name":"translate_informatsiya_so_spravochnika_","contentid":"box-block-show-info-by-directory","priority":"0","categoryname":"translate_name_and_issue_info","customSettings":"1","ismobile":"0","index":"4","integration":"","blockSettings":""},"188":{"id":"188","name":"translate_informatsiya_so_spravochnika_","contentid":"box-block-show-info-by-directory","priority":"0","categoryname":"translate_name_and_issue_info","customSettings":"1","ismobile":"0","index":"5","integration":"","blockSettings":""},"189":{"id":"189","name":"translate_aktivnie_spiski_produktov","contentid":"box-admin-block-order-active-productlists","priority":"0","categoryname":"translate_products","customSettings":"1","ismobile":"0","index":"0","integration":"","blockSettings":""},"190":{"id":"190","name":"translate_blok_informatsii_o_bonusakh_zakaza","contentid":"box-block-order-bonuse-info","priority":"0","categoryname":"translate_bonusi","customSettings":"1","ismobile":"0","index":"0","integration":"","blockSettings":""},"191":{"id":"191","name":"translate_yuridicheskie_rekviziti","contentid":"box-admin-block-order-client-legal","priority":"0","categoryname":"translate_name_and_issue_info","customSettings":"1","ismobile":"0","index":"0","integration":"","blockSettings":""},"192":{"id":"192","name":"translate_informatsiya_o_kompanii_klienta","contentid":"box-admin-block-order-client-company","priority":"0","categoryname":"translate_contacts_and_dop_pola","customSettings":"0","ismobile":"0","index":"0","integration":"","blockSettings":""},"193":{"id":"193","name":"translate_informatsiya_o_kholdinge_kompanii_klienta","contentid":"box-admin-block-order-client-holding-info","priority":"0","categoryname":"translate_contacts_and_dop_pola","customSettings":"1","ismobile":"0","index":"0","integration":"","blockSettings":""},"194":{"id":"194","name":"translate_struktura_kholdingovoy_kompanii_klienta","contentid":"box-admin-block-order-client-holding-structure","priority":"0","categoryname":"translate_useful","customSettings":"1","ismobile":"0","index":"0","integration":"","blockSettings":""},"195":{"id":"195","name":"translate_vibor_aktivnogo_sotrudnika_kompanii","contentid":"box-admin-block-order-client-company-employers","priority":"0","categoryname":"translate_contacts_and_dop_pola","customSettings":"1","ismobile":"0","index":"0","integration":"","blockSettings":""},"196":{"id":"196","name":"translate_avtor_zakaza","contentid":"box-admin-block-order-author","priority":"0","categoryname":"translate_name_and_issue_info","customSettings":"0","ismobile":"0","index":"0","integration":"","blockSettings":""},"197":{"id":"197","name":"translate_vivod_kontaktov_na_karte_google","contentid":"box-admin-block-search-user-in-order-map","priority":"0","categoryname":"translate_contacts_and_dop_pola","customSettings":"1","ismobile":"0","index":"0","integration":"","blockSettings":""},"198":{"id":"198","name":"translate_vivod_marshruta_po_podzadacham_na_karte","contentid":"box-admin-block-subissue-in-order-map","priority":"0","categoryname":"translate_contacts_and_dop_pola","customSettings":"1","ismobile":"0","index":"0","integration":"","blockSettings":""},"199":{"id":"199","name":"translate_adres_protsessa_na_karte_google","contentid":"box-admin-block-order-on-map","priority":"0","categoryname":"translate_contacts_and_dop_pola","customSettings":"0","ismobile":"0","index":"0","integration":"","blockSettings":""},"200":{"id":"200","name":"translate_poisk_addressa_v_meestexpress","contentid":"box-admin-block-search-address","priority":"0","categoryname":"translate_contacts_and_dop_pola","customSettings":"0","ismobile":"0","index":"0","integration":"","blockSettings":""},"201":{"id":"201","name":"translate_vstavka_koda_na_stranitsu","contentid":"box-admin-block-add-script","priority":"0","categoryname":"translate_contacts_and_dop_pola","customSettings":"1","ismobile":"0","index":"0","integration":"","blockSettings":""},"202":{"id":"202","name":"translate_vstavka_iframe_na_stranitsu","contentid":"box-admin-block-order-iframe","priority":"0","categoryname":"translate_proekt_and_other_bp","customSettings":"1","ismobile":"0","index":"0","integration":"","blockSettings":""},"203":{"id":"203","name":"translate_spisok_svyazannikh_kontaktov_iz_kartochki","contentid":"box-admin-block-list-contact-link-order-block","priority":"0","categoryname":"translate_contacts_and_dop_pola","customSettings":"1","ismobile":"0","index":"0","integration":"","blockSettings":""},"204":{"id":"204","name":"translate_poisk_klienta","contentid":"box-admin-block-search-client-order-block","priority":"0","categoryname":"translate_contacts_and_dop_pola","customSettings":"1","ismobile":"0","index":"0","integration":"","blockSettings":""},"205":{"id":"205","name":"translate_poisk_klienta","contentid":"box-admin-block-search-client-order-block","priority":"0","categoryname":"translate_contacts_and_dop_pola","customSettings":"1","ismobile":"0","index":"1","integration":"","blockSettings":""},"206":{"id":"206","name":"translate_poisk_klienta","contentid":"box-admin-block-search-client-order-block","priority":"0","categoryname":"translate_contacts_and_dop_pola","customSettings":"1","ismobile":"0","index":"2","integration":"","blockSettings":""},"207":{"id":"207","name":"translate_poisk_klienta","contentid":"box-admin-block-search-client-order-block","priority":"0","categoryname":"translate_contacts_and_dop_pola","customSettings":"1","ismobile":"0","index":"3","integration":"","blockSettings":""},"208":{"id":"208","name":"translate_poisk_klienta","contentid":"box-admin-block-search-client-order-block","priority":"0","categoryname":"translate_contacts_and_dop_pola","customSettings":"1","ismobile":"0","index":"4","integration":"","blockSettings":""},"209":{"id":"209","name":"translate_rekomendovanie_dochernie_kontakti","contentid":"box-admin-block-order-childs-users","priority":"0","categoryname":"translate_contacts_and_dop_pola","customSettings":"1","ismobile":"0","index":"0","integration":"","blockSettings":""},"210":{"id":"210","name":"translate_poslednie_zadachi_klienta","contentid":"box-admin-block-order-last-orders-client","priority":"0","categoryname":"translate_contacts_and_dop_pola","customSettings":"1","ismobile":"0","index":"0","integration":"","blockSettings":""},"211":{"id":"211","name":"translate_poslednie_zadachi_klienta","contentid":"box-admin-block-order-last-orders-client","priority":"0","categoryname":"translate_contacts_and_dop_pola","customSettings":"1","ismobile":"0","index":"1","integration":"","blockSettings":""},"212":{"id":"212","name":"translate_poslednie_zadachi_klienta","contentid":"box-admin-block-order-last-orders-client","priority":"0","categoryname":"translate_contacts_and_dop_pola","customSettings":"1","ismobile":"0","index":"2","integration":"","blockSettings":""},"213":{"id":"213","name":"translate_poslednie_zadachi_klienta","contentid":"box-admin-block-order-last-orders-client","priority":"0","categoryname":"translate_contacts_and_dop_pola","customSettings":"1","ismobile":"0","index":"3","integration":"","blockSettings":""},"214":{"id":"214","name":"translate_poslednie_zadachi_klienta","contentid":"box-admin-block-order-last-orders-client","priority":"0","categoryname":"translate_contacts_and_dop_pola","customSettings":"1","ismobile":"0","index":"4","integration":"","blockSettings":""},"215":{"id":"215","name":"translate_poslednie_biznesprotsessi_produkta_","contentid":"box-admin-block-order-orderproduct-last-orders-client","priority":"0","categoryname":"translate_proekt_and_other_bp","customSettings":"1","ismobile":"0","index":"0","integration":"","blockSettings":""},"216":{"id":"216","name":"translate_poslednie_biznesprotsessi_produkta_","contentid":"box-admin-block-order-orderproduct-last-orders-client","priority":"0","categoryname":"translate_proekt_and_other_bp","customSettings":"1","ismobile":"0","index":"1","integration":"","blockSettings":""},"217":{"id":"217","name":"translate_poslednie_biznesprotsessi_produkta_","contentid":"box-admin-block-order-orderproduct-last-orders-client","priority":"0","categoryname":"translate_proekt_and_other_bp","customSettings":"1","ismobile":"0","index":"2","integration":"","blockSettings":""},"218":{"id":"218","name":"translate_poslednie_biznesprotsessi_produkta_","contentid":"box-admin-block-order-orderproduct-last-orders-client","priority":"0","categoryname":"translate_proekt_and_other_bp","customSettings":"1","ismobile":"0","index":"3","integration":"","blockSettings":""},"219":{"id":"219","name":"translate_poslednie_biznesprotsessi_produkta_","contentid":"box-admin-block-order-orderproduct-last-orders-client","priority":"0","categoryname":"translate_proekt_and_other_bp","customSettings":"1","ismobile":"0","index":"4","integration":"","blockSettings":""},"220":{"id":"220","name":"translate_struktura_dochernikh_protsessov_karkasom","contentid":"box-admin-block-order-subissue-structure-grid","priority":"0","categoryname":"translate_proekt_and_other_bp","customSettings":"1","ismobile":"0","index":"0","integration":"","blockSettings":""},"221":{"id":"221","name":"translate_adresa_klienta_zakaza 1","contentid":"box-admin-block-order-address-client","priority":"0","categoryname":"translate_contacts_and_dop_pola","customSettings":"1","ismobile":"0","index":"0","integration":"","blockSettings":""},"222":{"id":"222","name":"translate_ispolniteli","contentid":"box-admin-block-order-employer","priority":"0","categoryname":"translate_proekt_and_other_bp","customSettings":"1","ismobile":"0","index":"0","integration":"","blockSettings":""},"223":{"id":"223","name":"translate_prosmotr_faylov","contentid":"box-admin-block-order-files-preview","priority":"0","categoryname":"translate_fayli_big","customSettings":"1","ismobile":"0","index":"0","integration":"","blockSettings":""},"224":{"id":"224","name":"translate_sdelat_snimok_s_vebkameri","contentid":"box-admin-block-add-foto-webcam-block","priority":"0","categoryname":"translate_contacts_and_dop_pola","customSettings":"1","ismobile":"0","index":"0","integration":"","blockSettings":""},"225":{"id":"225","name":"translate_blok_informatsii_o_nalichii_produktov_zakaza_na_sklade","contentid":"box-storage-order-block-orderproduct","priority":"0","categoryname":"translate_many_products","customSettings":"1","ismobile":"0","index":"0","integration":"","blockSettings":""},"226":{"id":"226","name":"translate_poisk_produkta_po_qr_kodu","contentid":"box-storage-search-qrcode-cell-and-product","priority":"0","categoryname":"translate_poisk_i_baza_znaniy","customSettings":"0","ismobile":"0","index":"0","integration":"","blockSettings":""},"227":{"id":"227","name":"translate_spisok_ozhidaemikh_platezhey_klienta_po_vsem_protsessam","contentid":"box-block-show-probation-payments","priority":"0","categoryname":"translate_ozhidaemie_platezhi","customSettings":"1","ismobile":"0","index":"0","integration":"","blockSettings":""},"228":{"id":"228","name":"translate_pereschet_ozhidaemih_platezhey","contentid":"box-block-recalculate-probabition-payments","priority":"0","categoryname":"translate_ozhidaemie_platezhi","customSettings":"1","ismobile":"0","index":"0","integration":"","blockSettings":""},"229":{"id":"229","name":"translate_byudzheti","contentid":"box-admin-block-order-budget-table","priority":"0","categoryname":"translate_cash","customSettings":"1","ismobile":"0","index":"0","integration":"","blockSettings":""},"230":{"id":"230","name":"translate_skachat_dokument_iz_ftpsftp","contentid":"box-admin-block-download-document-ftp","priority":"0","categoryname":"translate_documents","customSettings":"1","ismobile":"0","index":"0","integration":"","blockSettings":""},"231":{"id":"231","name":"translate_sformirovat_dokumenti","contentid":"box-admin-block-order-document-add","priority":"0","categoryname":"translate_documents","customSettings":"1","ismobile":"0","index":"0","integration":"","blockSettings":""},"232":{"id":"232","name":"translate_podpisat_dokument_etsp 0","contentid":"box-block-order-document-add-edc","priority":"0","categoryname":"translate_documents","customSettings":"1","ismobile":"0","index":"0","integration":"","blockSettings":""},"233":{"id":"233","name":"translate_podpisat_dokument_etsp 1","contentid":"box-block-order-document-add-edc","priority":"0","categoryname":"translate_documents","customSettings":"1","ismobile":"0","index":"1","integration":"","blockSettings":""},"234":{"id":"234","name":"translate_nastroyka_podpisi_etsp","contentid":"box-block-order-document-add-edc-setting","priority":"0","categoryname":"translate_documents","customSettings":"1","ismobile":"0","index":"0","integration":"","blockSettings":""},"235":{"id":"235","name":"translate_poluchit_informatsiyu_o_etsp_dokumenta","contentid":"box-block-order-document-get-edc","priority":"0","categoryname":"translate_documents","customSettings":"1","ismobile":"0","index":"0","integration":"","blockSettings":""},"236":{"id":"236","name":"translate_documents_table","contentid":"box-admin-block-order-document-list","priority":"0","categoryname":"translate_documents","customSettings":"1","ismobile":"0","index":"0","integration":"","blockSettings":""},"237":{"id":"237","name":"translate_podpisanti_dokumentov","contentid":"box-admin-block-order-document-signer","priority":"0","categoryname":"translate_documents","customSettings":"1","ismobile":"0","index":"0","integration":"","blockSettings":""},"238":{"id":"238","name":"translate_dobavit_podpisanta_dokumenta","contentid":"box-admin-block-order-document-signer-add","priority":"0","categoryname":"translate_documents","customSettings":"0","ismobile":"0","index":"0","integration":"","blockSettings":""},"239":{"id":"239","name":"translate_prosmotr_dokumentov","contentid":"box-admin-block-order-document-view","priority":"0","categoryname":"translate_documents","customSettings":"1","ismobile":"0","index":"0","integration":"","blockSettings":""},"240":{"id":"240","name":"Telegram \u0447\u0430\u0442 \u0441 \u043a\u043b\u0438\u0435\u043d\u0442\u043e\u043c \u043f\u0440\u043e\u0446\u0435\u0441\u0441\u0430","contentid":"box-admin-block-order-telegram-chat","priority":"0","categoryname":"Telegram","customSettings":"1","ismobile":"0","index":"0","integration":"telegram-integrations","blockSettings":""},"241":{"id":"241","name":"Viber \u0447\u0430\u0442 \u0441 \u043a\u043b\u0438\u0435\u043d\u0442\u043e\u043c \u043f\u0440\u043e\u0446\u0435\u0441\u0441\u0430","contentid":"box-admin-block-order-viber-chat","priority":"0","categoryname":"Viber","customSettings":"1","ismobile":"0","index":"0","integration":"viber","blockSettings":""},"242":{"id":"242","name":"translate_bistroe_bronirovanie_cherez_quiquo","contentid":"box-admin-block-order-contacts-send-qui-quo","priority":"0","categoryname":"translate_contacts_and_dop_pola","customSettings":"1","ismobile":"0","index":"0","integration":"quiquo-integrations","blockSettings":""},"243":{"id":"243","name":"translate_novaya_pochta","contentid":"box-admin-block-novaposhta","priority":"0","categoryname":"translate_dilivery_payment","customSettings":"0","ismobile":"0","index":"0","integration":"novaposhta-integration","blockSettings":""},"244":{"id":"244","name":"translate_parametri_ttn","contentid":"box-admin-block-novaposhta-invoice-settings","priority":"0","categoryname":"translate_dilivery_payment","customSettings":"1","ismobile":"0","index":"0","integration":"novaposhta-integration","blockSettings":""},"245":{"id":"245","name":"translate_parametri_otpravki","contentid":"box-admin-block-novaposhta-param","priority":"0","categoryname":"translate_dilivery_payment","customSettings":"1","ismobile":"0","index":"0","integration":"novaposhta-integration","blockSettings":""},"246":{"id":"246","name":"translate_universalniy_blok_","contentid":"mobile-block-universal-fillds","priority":"0","categoryname":"translate_universalnie_bloki","customSettings":"1","ismobile":"1","index":"0","integration":"","blockSettings":""},"247":{"id":"247","name":"translate_lenta_kommentariev","contentid":"mobile-block-comment-list","priority":"0","categoryname":"translate_universalnie_bloki","customSettings":"1","ismobile":"1","index":"0","integration":"","blockSettings":""},"248":{"id":"248","name":"translate_instruktsiya_k_etapu","contentid":"mobile-block-stage-instruction","priority":"0","categoryname":"translate_universalnie_bloki","customSettings":"1","ismobile":"1","index":"0","integration":"","blockSettings":""},"249":{"id":"249","name":"translate_blok_podprotsesov","contentid":"mobile-block-child-issue-table-view","priority":"0","categoryname":"translate_proekt_and_other_bp","customSettings":"1","ismobile":"1","index":"0","integration":"","blockSettings":""},"250":{"id":"250","name":"translate_dobavleniya_produkta_po_qr_kodu","contentid":"mobile-block-add-product-by-qrcode","priority":"0","categoryname":"translate_universalnie_bloki","customSettings":"1","ismobile":"1","index":"0","integration":"","blockSettings":""},"251":{"id":"251","name":"translate_dobavleniya_produkta_po_qr_kodu_i_ustanovka_emu_yacheyki_sklada","contentid":"mobile-block-add-product-and-cell-by-qrcode","priority":"0","categoryname":"translate_universalnie_bloki","customSettings":"1","ismobile":"1","index":"0","integration":"","blockSettings":""},"252":{"id":"252","name":"translate_peremeshchenie_produkta_na_yacheyku_sklada_verifier","contentid":"mobile-block-transfer-product-to-cell","priority":"0","categoryname":"translate_universalnie_bloki","customSettings":"1","ismobile":"1","index":"0","integration":"","blockSettings":""},"253":{"id":"253","name":"translate_oprikhodivat_produkti_v_vibrannuyu_yacheyku_sklada_checker","contentid":"mobile-block-add-incoming-product","priority":"0","categoryname":"translate_many_products","customSettings":"1","ismobile":"1","index":"0","integration":"","blockSettings":""},"254":{"id":"254","name":"translate_kolichestvo_produktov_protsessa_s_vibrannimi_znacheniyami_dopolnitelnikh_poley","contentid":"mobile-block-product-group-by-customfield","priority":"0","categoryname":"translate_many_products","customSettings":"1","ismobile":"1","index":"0","integration":"","blockSettings":""},"255":{"id":"255","name":"translate_blok_peremeshcheniya_produktov","contentid":"mobile-block-product-transfer","priority":"0","categoryname":"translate_many_products","customSettings":"1","ismobile":"1","index":"0","integration":"","blockSettings":""},"256":{"id":"256","name":"translate_order_products","contentid":"mobile-block-products","priority":"0","categoryname":"translate_many_products","customSettings":"1","ismobile":"1","index":"0","integration":"","blockSettings":""},"257":{"id":"257","name":"Justin \u0422\u0422\u041d","contentid":"box-admin-block-justin","priority":"0","categoryname":"translate_dilivery_payment","customSettings":"0","ismobile":"0","index":"0","integration":"justin-integration","blockSettings":""},"258":{"id":"258","name":"translate_blok_podprotsesov","contentid":"box-admin-block-child-issue-table-view","priority":"0","categoryname":"translate_proekt_and_other_bp","customSettings":"1","ismobile":"0","index":"1","integration":"","blockSettings":""},"259":{"id":"259","name":"translate_informatsiya_so_spravochnika_ 1","contentid":"box-block-show-info-by-directory","priority":"0","categoryname":"translate_name_and_issue_info","customSettings":"1","ismobile":"0","index":"1","integration":"","blockSettings":""},"260":{"id":"260","name":"translate_informatsiya_so_spravochnika_ 2","contentid":"box-block-show-info-by-directory","priority":"0","categoryname":"translate_name_and_issue_info","customSettings":"1","ismobile":"0","index":"2","integration":"","blockSettings":""},"261":{"id":"261","name":"translate_informatsiya_so_spravochnika_ 3","contentid":"box-block-show-info-by-directory","priority":"0","categoryname":"translate_name_and_issue_info","customSettings":"1","ismobile":"0","index":"3","integration":"","blockSettings":""},"262":{"id":"262","name":"translate_informatsiya_so_spravochnika_ 4","contentid":"box-block-show-info-by-directory","priority":"0","categoryname":"translate_name_and_issue_info","customSettings":"1","ismobile":"0","index":"4","integration":"","blockSettings":""},"263":{"id":"263","name":"translate_informatsiya_so_spravochnika_ 5","contentid":"box-block-show-info-by-directory","priority":"0","categoryname":"translate_name_and_issue_info","customSettings":"1","ismobile":"0","index":"5","integration":"","blockSettings":""},"264":{"id":"264","name":"translate_promo_code","contentid":"box-admin-order-use-coupon","priority":"0","categoryname":"translate_many_products","customSettings":"0","ismobile":"0","index":"0","integration":"","blockSettings":""},"265":{"id":"265","name":"\u0411\u043b\u043e\u043a \u043e\u043f\u0440\u043e\u0441\u0430","contentid":"vote-admin-block-vote","priority":"0","categoryname":"translate_proekt_and_other_bp","customSettings":"1","ismobile":"0","index":"0","integration":"vote-integration","blockSettings":""},"266":{"id":"266","name":"\u0421\u043e\u0437\u0434\u0430\u043d\u0438\u0435 \u043e\u043f\u0440\u043e\u0441\u0430","contentid":"vote-admin-block-create","priority":"0","categoryname":"translate_proekt_and_other_bp","customSettings":"1","ismobile":"0","index":"0","integration":"vote-integration","blockSettings":""},"267":{"id":"267","name":"\u0420\u0435\u0437\u0443\u043b\u044c\u0442\u0430\u0442\u044b \u043e\u043f\u0440\u043e\u0441\u0430","contentid":"vote-admin-block-results","priority":"0","categoryname":"translate_proekt_and_other_bp","customSettings":"1","ismobile":"0","index":"0","integration":"vote-integration","blockSettings":""},"268":{"id":"268","name":"translate_poslednee_pismo_klienta_svyazannoe_s_protsessom","contentid":"box-admin-block-client-linked-last-email","priority":"0","categoryname":"translate_contacts_and_dop_pola","customSettings":"1","ismobile":"0","index":"0","integration":"","blockSettings":""},"269":{"id":"269","name":"translate_polya_yuridicheskikh_rekvizitov_klienta","contentid":"box-block-order-universal-client-legal","priority":"0","categoryname":"translate_useful","customSettings":"1","ismobile":"0","index":"0","integration":"","blockSettings":""},"270":{"id":"270","name":"translate_related_products","contentid":"box-admin-block-order-products-related","priority":"0","categoryname":"translate_many_products","customSettings":"1","ismobile":"0","index":"0","integration":"","blockSettings":""},"271":{"id":"271","name":"translate_blok_podprotsesov","contentid":"box-admin-block-child-issue-table-view","priority":"0","categoryname":"translate_proekt_and_other_bp","customSettings":"1","ismobile":"0","index":"2","integration":"","blockSettings":""},"272":{"id":"272","name":"translate_derevo_proekta","contentid":"box-admin-block-project-tree","priority":"0","categoryname":"translate_proekt_and_other_bp","customSettings":"1","ismobile":"0","index":"0","integration":"","blockSettings":""},"273":{"id":"273","name":"translate_blok_podprotsesov","contentid":"box-admin-block-child-issue-table-view","priority":"0","categoryname":"translate_proekt_and_other_bp","customSettings":"1","ismobile":"0","index":"3","integration":"","blockSettings":""},"274":{"id":"274","name":"translate_kalkulyator_podbora_produktov_po_dopolnitelnim_polyam","contentid":"box-block-order-product-customfield-selection-calculator","priority":"0","categoryname":"translate_poisk_i_baza_znaniy","customSettings":"1","ismobile":"0","index":"0","integration":"","blockSettings":""},"275":{"id":"275","name":"translate_statistika_otpravlennikh_pisem_klientu_b2b_family","contentid":"b2bfamily-block-order-email-statistics","priority":"0","categoryname":"translate_sobitiy","customSettings":"1","ismobile":"0","index":"0","integration":"","blockSettings":""},"276":{"id":"276","name":"translate_adresa_klienta_zakaza 2","contentid":"box-admin-block-order-address-client","priority":"0","categoryname":"translate_contacts_and_dop_pola","customSettings":"1","ismobile":"0","index":"1","integration":"","blockSettings":""},"277":{"id":"277","name":"translate_sotrudniki_kompanii ","contentid":"box-block-order-company-employer","priority":"0","categoryname":"translate_useful","customSettings":"1","ismobile":"0","index":"0","integration":"","blockSettings":""},"278":{"id":"278","name":"translate_sotrudniki_kompanii ","contentid":"box-block-order-company-employer","priority":"0","categoryname":"translate_useful","customSettings":"1","ismobile":"0","index":"1","integration":"","blockSettings":""},"279":{"id":"279","name":"translate_sotrudniki_kompanii ","contentid":"box-block-order-company-employer","priority":"0","categoryname":"translate_useful","customSettings":"1","ismobile":"0","index":"2","integration":"","blockSettings":""},"280":{"id":"280","name":"translate_sotrudniki_kompanii ","contentid":"box-block-order-company-employer","priority":"0","categoryname":"translate_useful","customSettings":"1","ismobile":"0","index":"3","integration":"","blockSettings":""},"281":{"id":"281","name":"translate_sotrudniki_kompanii ","contentid":"box-block-order-company-employer","priority":"0","categoryname":"translate_useful","customSettings":"1","ismobile":"0","index":"4","integration":"","blockSettings":""},"282":{"id":"282","name":"\u0411\u043b\u043e\u043a \u043e\u0442\u043e\u0431\u0440\u0430\u0436\u0435\u043d\u0438\u044f UTM \u0434\u0430\u043d\u043d\u044b\u0445 \u043f\u0440\u043e\u0446\u0435\u0441\u0441\u0430 \u0438 \u043a\u043b\u0438\u0435\u043d\u0442\u0430 \u043f\u0440\u043e\u0446\u0435\u0441\u0441\u0430","contentid":"box-admin-block-order-usertraction-table","priority":"0","categoryname":"translate_useful","customSettings":"0","ismobile":"0","index":"0","integration":"","blockSettings":""},"283":{"id":"283","name":"\u0422\u0435\u043a\u0441\u0442 \u0438\u043b\u0438 HTML-\u043a\u043e\u0434","contentid":"box-admin-block-order-text","priority":"0","categoryname":"translate_useful","customSettings":"1","ismobile":"0","index":"1","integration":"","blockSettings":""},"284":{"id":"284","name":"\u0422\u0435\u043a\u0441\u0442 \u0438\u043b\u0438 HTML-\u043a\u043e\u0434","contentid":"box-admin-block-order-text","priority":"0","categoryname":"translate_useful","customSettings":"1","ismobile":"0","index":"2","integration":"","blockSettings":""},"285":{"id":"285","name":"\u0422\u0435\u043a\u0441\u0442 \u0438\u043b\u0438 HTML-\u043a\u043e\u0434","contentid":"box-admin-block-order-text","priority":"0","categoryname":"translate_useful","customSettings":"1","ismobile":"0","index":"3","integration":"","blockSettings":""},"286":{"id":"286","name":"\u0422\u0435\u043a\u0441\u0442 \u0438\u043b\u0438 HTML-\u043a\u043e\u0434","contentid":"box-admin-block-order-text","priority":"0","categoryname":"translate_useful","customSettings":"1","ismobile":"0","index":"4","integration":"","blockSettings":""},"287":{"id":"287","name":"\u0422\u0435\u043a\u0441\u0442 \u0438\u043b\u0438 HTML-\u043a\u043e\u0434","contentid":"box-admin-block-order-text","priority":"0","categoryname":"translate_useful","customSettings":"1","ismobile":"0","index":"5","integration":"","blockSettings":""},"288":{"id":"288","name":"\u0422\u0435\u043a\u0441\u0442 \u0438\u043b\u0438 HTML-\u043a\u043e\u0434","contentid":"box-admin-block-order-text","priority":"0","categoryname":"translate_useful","customSettings":"1","ismobile":"0","index":"6","integration":"","blockSettings":""},"289":{"id":"289","name":"\u0422\u0435\u043a\u0441\u0442 \u0438\u043b\u0438 HTML-\u043a\u043e\u0434","contentid":"box-admin-block-order-text","priority":"0","categoryname":"translate_useful","customSettings":"1","ismobile":"0","index":"7","integration":"","blockSettings":""},"290":{"id":"290","name":"\u0422\u0435\u043a\u0441\u0442 \u0438\u043b\u0438 HTML-\u043a\u043e\u0434","contentid":"box-admin-block-order-text","priority":"0","categoryname":"translate_useful","customSettings":"1","ismobile":"0","index":"8","integration":"","blockSettings":""},"291":{"id":"291","name":"\u0422\u0435\u043a\u0441\u0442 \u0438\u043b\u0438 HTML-\u043a\u043e\u0434","contentid":"box-admin-block-order-text","priority":"0","categoryname":"translate_useful","customSettings":"1","ismobile":"0","index":"9","integration":"","blockSettings":""},"292":{"id":"292","name":"\u0422\u0435\u043a\u0441\u0442 \u0438\u043b\u0438 HTML-\u043a\u043e\u0434","contentid":"box-admin-block-order-text","priority":"0","categoryname":"translate_useful","customSettings":"1","ismobile":"0","index":"10","integration":"","blockSettings":""},"293":{"id":"293","name":"\u041d\u0430\u0441\u0442\u0440\u043e\u0439\u043a\u0438 \u0434\u043e\u0441\u0442\u0430\u0432\u043a\u0438 Omniva","contentid":"box-admin-block-omniva-invoice-settings","priority":"0","categoryname":"Omniva","customSettings":"1","ismobile":"0","index":"0","integration":"omniva","blockSettings":""},"294":{"id":"294","name":"WebProduction \/ OneBox Next \/ \u0420\u0435\u043a\u043e\u043c\u0435\u043d\u0434\u0443\u0435\u043c\u044b\u0435 \u0438\u0441\u043f\u043e\u043b\u043d\u0438\u0442\u0435\u043b\u0438","contentid":"webproduction-block-orderai","priority":"0","categoryname":"translate_no_category","customSettings":"0","ismobile":"0","index":"0","integration":"","blockSettings":""},"295":{"id":"295","name":"\u0421\u043f\u0438\u0441\u043e\u043a \u0432\u0441\u0435\u0445 \u0431\u043e\u043d\u0443\u0441\u043e\u0432 \u043f\u043e \u043f\u0440\u043e\u0446\u0435\u0441\u0441\u0443","contentid":"webproduction-block-order-bonuses-list","priority":"0","categoryname":"translate_bonusi","customSettings":"0","ismobile":"0","index":"0","integration":"","blockSettings":""},"296":{"id":"296","name":"WebProduction \/ JAM \/ \u041f\u0440\u0435\u0434\u0441\u043a\u0430\u0437\u0430\u043d\u0438\u044f \u043f\u043e \u043f\u0440\u043e\u0435\u043a\u0442\u0430\u043c \u0432\u043d\u0435\u0434\u0440\u0435\u043d\u0438\u044f","contentid":"webproduction-block-predictions-for-implementation-jam","priority":"0","categoryname":"translate_no_category","customSettings":"1","ismobile":"0","index":"0","integration":"","blockSettings":""},"297":{"id":"297","name":"WebProduction \/ \u0410\u043f\u043d\u0443\u0442\u044c \u043f\u0440\u043e\u0435\u043a\u0442","contentid":"webproduction-block-gitup","priority":"0","categoryname":"translate_no_category","customSettings":"1","ismobile":"0","index":"0","integration":"","blockSettings":""},"298":{"id":"298","name":"WebProduction \/ \u0412\u044b\u0431\u0440\u0430\u043d\u043d\u044b\u0435 \u043f\u0440\u043e\u0446\u0435\u0441\u0441\u044b \u043f\u043e \u043a\u0430\u0442\u0435\u0433\u043e\u0440\u0438\u044f\u043c","contentid":"webproduction-block-checkedprocess2category","priority":"0","categoryname":"translate_no_category","customSettings":"1","ismobile":"0","index":"0","integration":"","blockSettings":""}},"change":{"2950":{"elementfromid":"510","elementtoid":"511"}}}